{"author": "Darcy Loane-Billings", "name": "darcy", "image": "../images/written/enjoy.jpg", "title": "Texte de Darcy", "words": 0,
  "text": "Lors de la préparation et de la construction du robot pour le Concours Vertigoal CRC 2019, l'équipe a rencontré plusieurs problèmes en cours de route, tels que la conception de la trieuse et les problèmes rencontrés avec les lumières LED que nous avons utilisées pour la trieuse. En effet, ces lumières nous ont retardés légèrement d’un point de vue électronique, mais heureusement, ce n’était pas vraiment un recul. Concernant le film (dont je suis responsable), un contretemps a été le test des différents microphones. Par exemple, nous avons tenté d’utiliser un micro à clipser, mais il était trop proche de la bouche de l’orateur en question et le son était trop fort. Lorsque nous avons abaissé ledit son, il devenait instable. Je dirais que l’un des plus grands sacrifices fait par l’équipe a été le temps. Effectivement, tout le monde a consacré beaucoup de temps et d’effort à la conception et à la construction du robot, du site web, du kiosque et du film. Cependant, je dirais que, dans l’ensemble, cela en valait la peine, puisque j’ai appris beaucoup de choses sur l'ingénierie. De plus, j’ai également eu beaucoup de plaisir!"}
